{
  "series_id": "company_viva_energy",
  "source_id": "company_viva_energy",
  "source_name": "Viva Energy Group annual report (ASX:VEA)",
  "source_url": "https://www.vivaenergy.com.au/investors/financial-results-reports",
  "unit": "",
  "retrieved_at": "2026-04-18T12:27:44+00:00",
  "last_data_point": null,
  "values": [],
  "notes": "Awaiting hand-keyed values from the named public source. Populate this file with figures copied directly from the publisher's latest report, keep 'manual_entry' set to true, and set 'status' to 'ok'.",
  "status": "unavailable",
  "manual_entry": true
}
