{
  "series_id": "company_santos",
  "source_id": "company_santos",
  "source_name": "Santos annual report (ASX:STO)",
  "source_url": "https://www.santos.com/investors/results-reports-and-presentations/",
  "unit": "",
  "retrieved_at": null,
  "last_data_point": null,
  "values": [],
  "notes": "Programmatic extractor could not produce a directly verifiable value.",
  "status": "unavailable",
  "manual_entry": false,
  "source_rights": "Company copyright",
  "citation": "Santos annual report.",
  "extra": {
    "schema": "programmatic_extractor_unavailable.v1",
    "fields": {
      "extractor": "fetch_via_manual_extractor",
      "resolved_url": "https://www.santos.com/investors/results-reports-and-presentations/",
      "reason": "HTTPError: 404 Client Error: Not Found for url: https://www.santos.com/investors/results-reports-and-presentations/"
    }
  }
}
